dimedbpy/__init__.py
dimedbpy/metabolite.py
dimedbpy/methods.py
dimedbpy-0.1.2.dist-info/LICENSE
dimedbpy-0.1.2.dist-info/METADATA
dimedbpy-0.1.2.dist-info/WHEEL
dimedbpy-0.1.2.dist-info/top_level.txt
dimedbpy-0.1.2.dist-info/RECORD
