Metadata-Version: 2.1
Name: dimedbpy
Version: 0.1.2
Summary: Python wrapper for DIMEdbs REST API.
Home-page: https://github.com/AberystwythSystemsBiology/dimedbpy
Author: Keiron OShea
Author-email: keo7@aber.ac.uk
License: UNKNOWN
Keywords: metabolomics,omics,processing
Platform: UNKNOWN
Classifier: Development Status :: 5 - Production/Stable
Classifier: Intended Audience :: Science/Research
Classifier: Programming Language :: Python :: 3
Classifier: Programming Language :: Python :: 3.5
Classifier: Programming Language :: Python :: 3.7
Classifier: Topic :: Scientific/Engineering :: Bio-Informatics
Classifier: License :: OSI Approved :: GNU General Public License v3 (GPLv3)
Classifier: Operating System :: OS Independent
Requires-Python: >=3
Requires-Dist: numpy (==1.18.1)
Requires-Dist: pandas (==0.25.0)
Requires-Dist: prettytable (==0.7.2)
Requires-Dist: requests (==2.24.0)
Requires-Dist: urllib3 (==1.25.10)
